phase_cli/__init__.py
phase_cli/exceptions.py
phase_cli/main.py
phase_cli/cmd/__init__.py
phase_cli/cmd/init.py
phase_cli/cmd/open_console.py
phase_cli/cmd/open_docs.py
phase_cli/cmd/run.py
phase_cli/cmd/shell.py
phase_cli/cmd/update.py
phase_cli/cmd/auth/__init__.py
phase_cli/cmd/auth/auth.py
phase_cli/cmd/auth/aws.py
phase_cli/cmd/secrets/__init__.py
phase_cli/cmd/secrets/create.py
phase_cli/cmd/secrets/delete.py
phase_cli/cmd/secrets/export.py
phase_cli/cmd/secrets/get.py
phase_cli/cmd/secrets/import_env.py
phase_cli/cmd/secrets/list.py
phase_cli/cmd/secrets/update.py
phase_cli/cmd/secrets/dynamic/__init__.py
phase_cli/cmd/secrets/dynamic/list_dynamic.py
phase_cli/cmd/secrets/dynamic/list/__init__.py
phase_cli/cmd/secrets/dynamic/list/lease_generate.py
phase_cli/cmd/secrets/dynamic/list/lease_get.py
phase_cli/cmd/secrets/dynamic/list/lease_renew.py
phase_cli/cmd/secrets/dynamic/list/lease_revoke.py
phase_cli/cmd/users/__init__.py
phase_cli/cmd/users/keyring.py
phase_cli/cmd/users/logout.py
phase_cli/cmd/users/switch.py
phase_cli/cmd/users/whoami.py
phase_cli/utils/__init__.py
phase_cli/utils/const.py
phase_cli/utils/crypto.py
phase_cli/utils/keyring.py
phase_cli/utils/misc.py
phase_cli/utils/network.py
phase_cli/utils/phase_io.py
phase_cli/utils/secret_referencing.py
phase_cli-1.21.1.dist-info/licenses/LICENSE
phase_cli-1.21.1.dist-info/METADATA
phase_cli-1.21.1.dist-info/WHEEL
phase_cli-1.21.1.dist-info/entry_points.txt
phase_cli-1.21.1.dist-info/top_level.txt
phase_cli-1.21.1.dist-info/RECORD
