Metadata-Version: 2.4
Name: phase_cli
Version: 1.21.1
Summary: Securely manage your secrets and environment variables with Phase.
Home-page: https://github.com/phasehq/cli
Author: Phase
Author-email: info@phase.dev
Classifier: Programming Language :: Python :: 3
Classifier: License :: OSI Approved :: GNU General Public License v3 (GPLv3)
Classifier: Operating System :: OS Independent
Requires-Python: >=3.9
License-File: LICENSE
Requires-Dist: keyring==25.6.0
Requires-Dist: questionary==2.1.1
Requires-Dist: cffi==1.17.1
Requires-Dist: requests==2.32.5
Requires-Dist: PyNaCl==1.6.0
Requires-Dist: rich==14.1.0
Requires-Dist: botocore>=1.40.17
Requires-Dist: pyyaml==6.0.3
Dynamic: author
Dynamic: author-email
Dynamic: classifier
Dynamic: description
Dynamic: description-content-type
Dynamic: home-page
Dynamic: license-file
Dynamic: requires-dist
Dynamic: requires-python
Dynamic: summary
